[
  {
    "nhs": "6538586104",
    "name": "Laryssa Vasilik",
    "doctor": "Dr. Noak Kyrkeman",
    "doctorEmail": "nkyrkeman3@foxnews.com",
    "doctorId": 4,
    "patientEmail": "lvasilik0@java.com",
    "items": [
      {
        "date": "2026-08-08",
        "time": "13:45",
        "type": "General Check-up",
        "desc": "Routine health screening and vitals",
        "doctorEmail": "nkyrkeman3@foxnews.com",
        "doctorId": 4
      },
      {
        "date": "2026-12-19",
        "time": "10:15",
        "type": "Follow-up",
        "desc": "Review of recent results and symptoms",
        "doctorEmail": "vrilton0@discuz.net",
        "doctorId": 1
      }
    ]
  },
  {
    "nhs": "3748194617",
    "name": "Maurita Charke",
    "doctor": "Dr. Cordell Toor",
    "doctorEmail": "ctoorb@psu.edu",
    "doctorId": 12,
    "patientEmail": "mcharke1@cafepress.com",
    "items": [
      {
        "date": "2026-01-04",
        "time": "13:00",
        "type": "ENT Examination",
        "desc": "Ear, nose and throat review",
        "doctorEmail": "ctoorb@psu.edu",
        "doctorId": 12
      },
      {
        "date": "2026-06-03",
        "time": "09:45",
        "type": "General Check-up",
        "desc": "Routine health screening and vitals",
        "doctorEmail": "sgivese@wsj.com",
        "doctorId": 15
      },
      {
        "date": "2026-06-03",
        "time": "08:00",
        "type": "Neurology",
        "desc": "Headache, dizziness and neuro exam",
        "doctorEmail": "zgalloway7@ca.gov",
        "doctorId": 8
      }
    ]
  },
  {
    "nhs": "1055801944",
    "name": "Aeriell Norvill",
    "doctor": "Dr. Ettie Beardsworth",
    "doctorEmail": "ebeardsworth1@mac.com",
    "doctorId": 2,
    "patientEmail": "anorvill2@msn.com",
    "items": [
      {
        "date": "2026-05-10",
        "time": "10:15",
        "type": "Physiotherapy",
        "desc": "Mobility, pain and exercise plan",
        "doctorEmail": "ebeardsworth1@mac.com",
        "doctorId": 2
      },
      {
        "date": "2026-10-15",
        "time": "15:00",
        "type": "Physiotherapy",
        "desc": "Mobility, pain and exercise plan",
        "doctorEmail": "emcquillan2@about.me",
        "doctorId": 3
      }
    ]
  },
  {
    "nhs": "2842736109",
    "name": "Aubrey Dunston",
    "doctor": "Dr. Ettie Beardsworth",
    "doctorEmail": "ebeardsworth1@mac.com",
    "doctorId": 2,
    "patientEmail": "adunston3@bigcartel.com",
    "items": [
      {
        "date": "2026-02-27",
        "time": "15:30",
        "type": "Hypertension Review",
        "desc": "BP trend review and medication",
        "doctorEmail": "ebeardsworth1@mac.com",
        "doctorId": 2
      },
      {
        "date": "2026-08-10",
        "time": "09:15",
        "type": "Dental Cleaning",
        "desc": "Teeth cleaning and cavity inspection",
        "doctorEmail": "nkyrkeman3@foxnews.com",
        "doctorId": 4
      },
      {
        "date": "2026-11-27",
        "time": "16:15",
        "type": "Dermatology",
        "desc": "Skin inspection and treatment planning",
        "doctorEmail": "nkyrkeman3@foxnews.com",
        "doctorId": 4
      }
    ]
  },
  {
    "nhs": "4315792829",
    "name": "Emanuele Duncanson",
    "doctor": "Dr. Noak Kyrkeman",
    "doctorEmail": "nkyrkeman3@foxnews.com",
    "doctorId": 4,
    "patientEmail": "eduncanson4@liveinternet.ru",
    "items": [
      {
        "date": "2025-12-04",
        "time": "13:45",
        "type": "Neurology",
        "desc": "Headache, dizziness and neuro exam",
        "doctorEmail": "nkyrkeman3@foxnews.com",
        "doctorId": 4
      },
      {
        "date": "2026-02-18",
        "time": "12:15",
        "type": "Hypertension Review",
        "desc": "BP trend review and medication",
        "doctorEmail": "zgalloway7@ca.gov",
        "doctorId": 8
      },
      {
        "date": "2026-07-31",
        "time": "08:15",
        "type": "Neurology",
        "desc": "Headache, dizziness and neuro exam",
        "doctorEmail": "hwillingamc@springer.com",
        "doctorId": 13
      }
    ]
  },
  {
    "nhs": "6703065764",
    "name": "Rudie Theurer",
    "doctor": "Dr. Rowland Blount",
    "doctorEmail": "rblount8@pen.io",
    "doctorId": 9,
    "patientEmail": "rtheurer5@google.ca",
    "items": [
      {
        "date": "2026-03-05",
        "time": "14:30",
        "type": "Follow-up",
        "desc": "Review of recent results and symptoms",
        "doctorEmail": "rblount8@pen.io",
        "doctorId": 9
      },
      {
        "date": "2026-06-19",
        "time": "10:15",
        "type": "General Check-up",
        "desc": "Routine health screening and vitals",
        "doctorEmail": "hwillingamc@springer.com",
        "doctorId": 13
      }
    ]
  },
  {
    "nhs": "9930757538",
    "name": "Randall Kuna",
    "doctor": "Dr. Erwin Handlin",
    "doctorEmail": "ehandlin4@gravatar.com",
    "doctorId": 5,
    "patientEmail": "rkuna6@ted.com",
    "items": [
      {
        "date": "2026-01-03",
        "time": "10:15",
        "type": "Dermatology",
        "desc": "Skin inspection and treatment planning",
        "doctorEmail": "ehandlin4@gravatar.com",
        "doctorId": 5
      },
      {
        "date": "2026-05-29",
        "time": "16:30",
        "type": "Ophthalmology",
        "desc": "Vision assessment and lens/eye health",
        "doctorEmail": "nkyrkeman3@foxnews.com",
        "doctorId": 4
      }
    ]
  },
  {
    "nhs": "6412244999",
    "name": "Brnaba Claridge",
    "doctor": "Dr. Irvin Dumberrill",
    "doctorEmail": "idumberrilld@toplist.cz",
    "doctorId": 14,
    "patientEmail": "bclaridge7@latimes.com",
    "items": [
      {
        "date": "2026-06-26",
        "time": "13:15",
        "type": "Cardiology Consultation",
        "desc": "Discuss chest discomfort and risk factors",
        "doctorEmail": "idumberrilld@toplist.cz",
        "doctorId": 14
      },
      {
        "date": "2026-08-25",
        "time": "12:45",
        "type": "Vaccination",
        "desc": "Routine immunization booster",
        "doctorEmail": "zgalloway7@ca.gov",
        "doctorId": 8
      },
      {
        "date": "2026-08-29",
        "time": "16:00",
        "type": "Cardiology Consultation",
        "desc": "Discuss chest discomfort and risk factors",
        "doctorEmail": "rphilipard6@mayoclinic.com",
        "doctorId": 7
      }
    ]
  },
  {
    "nhs": "1937225747",
    "name": "Dre Puffett",
    "doctor": "Dr. Merrily Harmson",
    "doctorEmail": "mharmsona@i2i.jp",
    "doctorId": 11,
    "patientEmail": "dpuffett8@baidu.com",
    "items": [
      {
        "date": "2026-01-26",
        "time": "13:15",
        "type": "General Check-up",
        "desc": "Routine health screening and vitals",
        "doctorEmail": "mharmsona@i2i.jp",
        "doctorId": 11
      },
      {
        "date": "2026-05-19",
        "time": "09:30",
        "type": "Pediatrics",
        "desc": "Child growth, vaccination and development",
        "doctorEmail": "ehandlin4@gravatar.com",
        "doctorId": 5
      }
    ]
  },
  {
    "nhs": "0834678659",
    "name": "Vivi Pilch",
    "doctor": "Dr. Irvin Dumberrill",
    "doctorEmail": "idumberrilld@toplist.cz",
    "doctorId": 14,
    "patientEmail": "vpilch9@dell.com",
    "items": [
      {
        "date": "2026-08-01",
        "time": "11:45",
        "type": "Orthopedics",
        "desc": "Joint/muscle pain assessment",
        "doctorEmail": "idumberrilld@toplist.cz",
        "doctorId": 14
      },
      {
        "date": "2026-09-15",
        "time": "11:15",
        "type": "General Check-up",
        "desc": "Routine health screening and vitals",
        "doctorEmail": "emcquillan2@about.me",
        "doctorId": 3
      }
    ]
  },
  {
    "nhs": "8440179340",
    "name": "Ferris Gowenlock",
    "doctor": "Dr. Noak Kyrkeman",
    "doctorEmail": "nkyrkeman3@foxnews.com",
    "doctorId": 4,
    "patientEmail": "fgowenlocka@gmpg.org",
    "items": [
      {
        "date": "2026-09-28",
        "time": "12:45",
        "type": "Hypertension Review",
        "desc": "BP trend review and medication",
        "doctorEmail": "nkyrkeman3@foxnews.com",
        "doctorId": 4
      },
      {
        "date": "2026-12-07",
        "time": "15:15",
        "type": "Dermatology",
        "desc": "Skin inspection and treatment planning",
        "doctorEmail": "hwillingamc@springer.com",
        "doctorId": 13
      }
    ]
  },
  {
    "nhs": "9427293039",
    "name": "Gerry Dreier",
    "doctor": "Dr. Zoe Galloway",
    "doctorEmail": "zgalloway7@ca.gov",
    "doctorId": 8,
    "patientEmail": "gdreierb@microsoft.com",
    "items": [
      {
        "date": "2026-04-14",
        "time": "11:30",
        "type": "Hypertension Review",
        "desc": "BP trend review and medication",
        "doctorEmail": "zgalloway7@ca.gov",
        "doctorId": 8
      },
      {
        "date": "2026-06-16",
        "time": "09:00",
        "type": "Pediatrics",
        "desc": "Child growth, vaccination and development",
        "doctorEmail": "zgalloway7@ca.gov",
        "doctorId": 8
      }
    ]
  },
  {
    "nhs": "3795743850",
    "name": "Huntington Macartney",
    "doctor": "Dr. Irvin Dumberrill",
    "doctorEmail": "idumberrilld@toplist.cz",
    "doctorId": 14,
    "patientEmail": "hmacartneyc@sitemeter.com",
    "items": [
      {
        "date": "2026-04-07",
        "time": "08:00",
        "type": "General Check-up",
        "desc": "Routine health screening and vitals",
        "doctorEmail": "idumberrilld@toplist.cz",
        "doctorId": 14
      },
      {
        "date": "2026-08-29",
        "time": "15:15",
        "type": "Physiotherapy",
        "desc": "Mobility, pain and exercise plan",
        "doctorEmail": "rblount8@pen.io",
        "doctorId": 9
      },
      {
        "date": "2026-09-10",
        "time": "16:00",
        "type": "Neurology",
        "desc": "Headache, dizziness and neuro exam",
        "doctorEmail": "rblount8@pen.io",
        "doctorId": 9
      }
    ]
  },
  {
    "nhs": "0176749152",
    "name": "Terry Litel",
    "doctor": "Dr. Cordell Toor",
    "doctorEmail": "ctoorb@psu.edu",
    "doctorId": 12,
    "patientEmail": "tliteld@wikipedia.org",
    "items": [
      {
        "date": "2026-03-13",
        "time": "12:15",
        "type": "Follow-up",
        "desc": "Review of recent results and symptoms",
        "doctorEmail": "ctoorb@psu.edu",
        "doctorId": 12
      },
      {
        "date": "2026-05-24",
        "time": "14:45",
        "type": "Physiotherapy",
        "desc": "Mobility, pain and exercise plan",
        "doctorEmail": "zgalloway7@ca.gov",
        "doctorId": 8
      }
    ]
  },
  {
    "nhs": "4647088979",
    "name": "Thorvald Salzberger",
    "doctor": "Dr. Erwin Handlin",
    "doctorEmail": "ehandlin4@gravatar.com",
    "doctorId": 5,
    "patientEmail": "tsalzbergere@npr.org",
    "items": [
      {
        "date": "2025-11-15",
        "time": "16:00",
        "type": "Physiotherapy",
        "desc": "Mobility, pain and exercise plan",
        "doctorEmail": "ehandlin4@gravatar.com",
        "doctorId": 5
      },
      {
        "date": "2025-11-28",
        "time": "12:30",
        "type": "Cardiology Consultation",
        "desc": "Discuss chest discomfort and risk factors",
        "doctorEmail": "spawling9@princeton.edu",
        "doctorId": 10
      },
      {
        "date": "2026-11-22",
        "time": "13:45",
        "type": "Physiotherapy",
        "desc": "Mobility, pain and exercise plan",
        "doctorEmail": "mcaghy5@surveymonkey.com",
        "doctorId": 6
      }
    ]
  },
  {
    "nhs": "7256963432",
    "name": "Kinsley Lygo",
    "doctor": "Dr. Noak Kyrkeman",
    "doctorEmail": "nkyrkeman3@foxnews.com",
    "doctorId": 4,
    "patientEmail": "klygof@theguardian.com",
    "items": [
      {
        "date": "2025-11-22",
        "time": "13:00",
        "type": "General Check-up",
        "desc": "Routine health screening and vitals",
        "doctorEmail": "nkyrkeman3@foxnews.com",
        "doctorId": 4
      },
      {
        "date": "2026-03-02",
        "time": "10:45",
        "type": "Follow-up",
        "desc": "Review of recent results and symptoms",
        "doctorEmail": "nkyrkeman3@foxnews.com",
        "doctorId": 4
      }
    ]
  },
  {
    "nhs": "4054087388",
    "name": "Waverly Soigoux",
    "doctor": "Dr. Irvin Dumberrill",
    "doctorEmail": "idumberrilld@toplist.cz",
    "doctorId": 14,
    "patientEmail": "wsoigouxg@homestead.com",
    "items": [
      {
        "date": "2026-03-22",
        "time": "16:15",
        "type": "ENT Examination",
        "desc": "Ear, nose and throat review",
        "doctorEmail": "idumberrilld@toplist.cz",
        "doctorId": 14
      },
      {
        "date": "2026-03-30",
        "time": "10:15",
        "type": "Physiotherapy",
        "desc": "Mobility, pain and exercise plan",
        "doctorEmail": "rblount8@pen.io",
        "doctorId": 9
      },
      {
        "date": "2026-07-09",
        "time": "10:30",
        "type": "Follow-up",
        "desc": "Review of recent results and symptoms",
        "doctorEmail": "ehandlin4@gravatar.com",
        "doctorId": 5
      }
    ]
  },
  {
    "nhs": "1487623658",
    "name": "Ardeen Cicullo",
    "doctor": "Dr. Rowland Blount",
    "doctorEmail": "rblount8@pen.io",
    "doctorId": 9,
    "patientEmail": "aciculloh@eepurl.com",
    "items": [
      {
        "date": "2026-10-06",
        "time": "11:15",
        "type": "Ophthalmology",
        "desc": "Vision assessment and lens/eye health",
        "doctorEmail": "rblount8@pen.io",
        "doctorId": 9
      },
      {
        "date": "2026-10-28",
        "time": "12:45",
        "type": "Hypertension Review",
        "desc": "BP trend review and medication",
        "doctorEmail": "ehandlin4@gravatar.com",
        "doctorId": 5
      }
    ]
  },
  {
    "nhs": "3906914518",
    "name": "Andras Cox",
    "doctor": "Dr. Monah Caghy",
    "doctorEmail": "mcaghy5@surveymonkey.com",
    "doctorId": 6,
    "patientEmail": "acoxi@cargocollective.com",
    "items": [
      {
        "date": "2025-12-30",
        "time": "15:00",
        "type": "Dermatology",
        "desc": "Skin inspection and treatment planning",
        "doctorEmail": "mcaghy5@surveymonkey.com",
        "doctorId": 6
      },
      {
        "date": "2026-01-20",
        "time": "11:30",
        "type": "ENT Examination",
        "desc": "Ear, nose and throat review",
        "doctorEmail": "sgivese@wsj.com",
        "doctorId": 15
      },
      {
        "date": "2026-11-01",
        "time": "15:45",
        "type": "Dental Cleaning",
        "desc": "Teeth cleaning and cavity inspection",
        "doctorEmail": "ehandlin4@gravatar.com",
        "doctorId": 5
      }
    ]
  },
  {
    "nhs": "9516004776",
    "name": "Huntington Trownson",
    "doctor": "Dr. Rowland Blount",
    "doctorEmail": "rblount8@pen.io",
    "doctorId": 9,
    "patientEmail": "htrownsonj@redcross.org",
    "items": [
      {
        "date": "2026-06-10",
        "time": "15:00",
        "type": "Diabetes Review",
        "desc": "HbA1c review, medication and diet",
        "doctorEmail": "rblount8@pen.io",
        "doctorId": 9
      },
      {
        "date": "2026-12-29",
        "time": "11:30",
        "type": "Hypertension Review",
        "desc": "BP trend review and medication",
        "doctorEmail": "zgalloway7@ca.gov",
        "doctorId": 8
      }
    ]
  },
  {
    "nhs": "4063756793",
    "name": "Erda Farfalameev",
    "doctor": "Dr. Cordell Toor",
    "doctorEmail": "ctoorb@psu.edu",
    "doctorId": 12,
    "patientEmail": "efarfalameevk@upenn.edu",
    "items": [
      {
        "date": "2026-08-16",
        "time": "09:00",
        "type": "Hypertension Review",
        "desc": "BP trend review and medication",
        "doctorEmail": "ctoorb@psu.edu",
        "doctorId": 12
      },
      {
        "date": "2026-12-26",
        "time": "08:15",
        "type": "Vaccination",
        "desc": "Routine immunization booster",
        "doctorEmail": "spawling9@princeton.edu",
        "doctorId": 10
      }
    ]
  },
  {
    "nhs": "7955347048",
    "name": "Tadeo Dunlop",
    "doctor": "Dr. Cordell Toor",
    "doctorEmail": "ctoorb@psu.edu",
    "doctorId": 12,
    "patientEmail": "tdunlopl@xing.com",
    "items": [
      {
        "date": "2026-07-08",
        "time": "10:00",
        "type": "Orthopedics",
        "desc": "Joint/muscle pain assessment",
        "doctorEmail": "ctoorb@psu.edu",
        "doctorId": 12
      },
      {
        "date": "2026-12-15",
        "time": "13:30",
        "type": "ENT Examination",
        "desc": "Ear, nose and throat review",
        "doctorEmail": "mcaghy5@surveymonkey.com",
        "doctorId": 6
      }
    ]
  },
  {
    "nhs": "5954675740",
    "name": "Susannah Jobke",
    "doctor": "Dr. Hi Willingam",
    "doctorEmail": "hwillingamc@springer.com",
    "doctorId": 13,
    "patientEmail": "sjobkem@theguardian.com",
    "items": [
      {
        "date": "2025-11-14",
        "time": "09:45",
        "type": "Ophthalmology",
        "desc": "Vision assessment and lens/eye health",
        "doctorEmail": "hwillingamc@springer.com",
        "doctorId": 13
      },
      {
        "date": "2026-03-26",
        "time": "09:30",
        "type": "Vaccination",
        "desc": "Routine immunization booster",
        "doctorEmail": "mcaghy5@surveymonkey.com",
        "doctorId": 6
      },
      {
        "date": "2026-12-06",
        "time": "11:15",
        "type": "Vaccination",
        "desc": "Routine immunization booster",
        "doctorEmail": "mcaghy5@surveymonkey.com",
        "doctorId": 6
      }
    ]
  },
  {
    "nhs": "3958557031",
    "name": "Ellette Dyter",
    "doctor": "Dr. Rad Philipard",
    "doctorEmail": "rphilipard6@mayoclinic.com",
    "doctorId": 7,
    "patientEmail": "edytern@cdbaby.com",
    "items": [
      {
        "date": "2026-09-10",
        "time": "10:45",
        "type": "Orthopedics",
        "desc": "Joint/muscle pain assessment",
        "doctorEmail": "rphilipard6@mayoclinic.com",
        "doctorId": 7
      },
      {
        "date": "2026-10-22",
        "time": "08:30",
        "type": "Orthopedics",
        "desc": "Joint/muscle pain assessment",
        "doctorEmail": "mcaghy5@surveymonkey.com",
        "doctorId": 6
      }
    ]
  },
  {
    "nhs": "5430525790",
    "name": "Falito Oakeby",
    "doctor": "Dr. Zoe Galloway",
    "doctorEmail": "zgalloway7@ca.gov",
    "doctorId": 8,
    "patientEmail": "foakebyo@blog.com",
    "items": [
      {
        "date": "2026-04-04",
        "time": "12:30",
        "type": "Vaccination",
        "desc": "Routine immunization booster",
        "doctorEmail": "zgalloway7@ca.gov",
        "doctorId": 8
      },
      {
        "date": "2026-06-01",
        "time": "10:00",
        "type": "Physiotherapy",
        "desc": "Mobility, pain and exercise plan",
        "doctorEmail": "vrilton0@discuz.net",
        "doctorId": 1
      },
      {
        "date": "2026-10-02",
        "time": "16:45",
        "type": "Follow-up",
        "desc": "Review of recent results and symptoms",
        "doctorEmail": "rblount8@pen.io",
        "doctorId": 9
      }
    ]
  },
  {
    "nhs": "2755133783",
    "name": "Euphemia Baltzar",
    "doctor": "Dr. Si Pawling",
    "doctorEmail": "spawling9@princeton.edu",
    "doctorId": 10,
    "patientEmail": "ebaltzarp@jimdo.com",
    "items": [
      {
        "date": "2026-06-06",
        "time": "12:30",
        "type": "Cardiology Consultation",
        "desc": "Discuss chest discomfort and risk factors",
        "doctorEmail": "spawling9@princeton.edu",
        "doctorId": 10
      },
      {
        "date": "2026-06-26",
        "time": "11:15",
        "type": "Orthopedics",
        "desc": "Joint/muscle pain assessment",
        "doctorEmail": "hwillingamc@springer.com",
        "doctorId": 13
      }
    ]
  },
  {
    "nhs": "3927052396",
    "name": "Gardner Fidge",
    "doctor": "Dr. Rad Philipard",
    "doctorEmail": "rphilipard6@mayoclinic.com",
    "doctorId": 7,
    "patientEmail": "gfidgeq@nhs.uk",
    "items": [
      {
        "date": "2026-07-01",
        "time": "13:00",
        "type": "General Check-up",
        "desc": "Routine health screening and vitals",
        "doctorEmail": "rphilipard6@mayoclinic.com",
        "doctorId": 7
      },
      {
        "date": "2026-11-28",
        "time": "11:15",
        "type": "General Check-up",
        "desc": "Routine health screening and vitals",
        "doctorEmail": "ehandlin4@gravatar.com",
        "doctorId": 5
      }
    ]
  },
  {
    "nhs": "9672170890",
    "name": "Bud Eastabrook",
    "doctor": "Dr. Noak Kyrkeman",
    "doctorEmail": "nkyrkeman3@foxnews.com",
    "doctorId": 4,
    "patientEmail": "beastabrookr@prweb.com",
    "items": [
      {
        "date": "2026-03-30",
        "time": "13:15",
        "type": "Ophthalmology",
        "desc": "Vision assessment and lens/eye health",
        "doctorEmail": "nkyrkeman3@foxnews.com",
        "doctorId": 4
      },
      {
        "date": "2026-07-24",
        "time": "08:00",
        "type": "ENT Examination",
        "desc": "Ear, nose and throat review",
        "doctorEmail": "ctoorb@psu.edu",
        "doctorId": 12
      },
      {
        "date": "2026-08-04",
        "time": "10:30",
        "type": "Orthopedics",
        "desc": "Joint/muscle pain assessment",
        "doctorEmail": "ctoorb@psu.edu",
        "doctorId": 12
      }
    ]
  },
  {
    "nhs": "3298389188",
    "name": "Shel O'Crigan",
    "doctor": "Dr. Stafani Gives",
    "doctorEmail": "sgivese@wsj.com",
    "doctorId": 15,
    "patientEmail": "socrigans@feedburner.com",
    "items": [
      {
        "date": "2026-07-16",
        "time": "11:15",
        "type": "Vaccination",
        "desc": "Routine immunization booster",
        "doctorEmail": "sgivese@wsj.com",
        "doctorId": 15
      },
      {
        "date": "2026-08-21",
        "time": "10:15",
        "type": "Follow-up",
        "desc": "Review of recent results and symptoms",
        "doctorEmail": "ebeardsworth1@mac.com",
        "doctorId": 2
      }
    ]
  },
  {
    "nhs": "0166036064",
    "name": "Jory Caneo",
    "doctor": "Dr. Merrily Harmson",
    "doctorEmail": "mharmsona@i2i.jp",
    "doctorId": 11,
    "patientEmail": "jcaneot@senate.gov",
    "items": [
      {
        "date": "2026-02-15",
        "time": "08:15",
        "type": "Pediatrics",
        "desc": "Child growth, vaccination and development",
        "doctorEmail": "mharmsona@i2i.jp",
        "doctorId": 11
      },
      {
        "date": "2026-07-29",
        "time": "10:45",
        "type": "Dermatology",
        "desc": "Skin inspection and treatment planning",
        "doctorEmail": "hwillingamc@springer.com",
        "doctorId": 13
      }
    ]
  },
  {
    "nhs": "7495367466",
    "name": "Charles Meharg",
    "doctor": "Dr. Hi Willingam",
    "doctorEmail": "hwillingamc@springer.com",
    "doctorId": 13,
    "patientEmail": "cmehargu@accuweather.com",
    "items": [
      {
        "date": "2026-06-28",
        "time": "14:15",
        "type": "Dermatology",
        "desc": "Skin inspection and treatment planning",
        "doctorEmail": "hwillingamc@springer.com",
        "doctorId": 13
      },
      {
        "date": "2026-11-29",
        "time": "11:15",
        "type": "Hypertension Review",
        "desc": "BP trend review and medication",
        "doctorEmail": "idumberrilld@toplist.cz",
        "doctorId": 14
      }
    ]
  },
  {
    "nhs": "2802706446",
    "name": "Murielle Abel",
    "doctor": "Dr. Emera McQuillan",
    "doctorEmail": "emcquillan2@about.me",
    "doctorId": 3,
    "patientEmail": "mabelv@jiathis.com",
    "items": [
      {
        "date": "2026-07-23",
        "time": "16:30",
        "type": "Dermatology",
        "desc": "Skin inspection and treatment planning",
        "doctorEmail": "emcquillan2@about.me",
        "doctorId": 3
      },
      {
        "date": "2026-08-02",
        "time": "15:00",
        "type": "General Check-up",
        "desc": "Routine health screening and vitals",
        "doctorEmail": "nkyrkeman3@foxnews.com",
        "doctorId": 4
      },
      {
        "date": "2026-08-22",
        "time": "12:15",
        "type": "Ophthalmology",
        "desc": "Vision assessment and lens/eye health",
        "doctorEmail": "sgivese@wsj.com",
        "doctorId": 15
      }
    ]
  },
  {
    "nhs": "4009273895",
    "name": "Virginie Trynor",
    "doctor": "Dr. Stafani Gives",
    "doctorEmail": "sgivese@wsj.com",
    "doctorId": 15,
    "patientEmail": "vtrynorw@merriam-webster.com",
    "items": [
      {
        "date": "2026-01-22",
        "time": "09:15",
        "type": "Diabetes Review",
        "desc": "HbA1c review, medication and diet",
        "doctorEmail": "sgivese@wsj.com",
        "doctorId": 15
      },
      {
        "date": "2026-08-23",
        "time": "16:30",
        "type": "Diabetes Review",
        "desc": "HbA1c review, medication and diet",
        "doctorEmail": "ehandlin4@gravatar.com",
        "doctorId": 5
      }
    ]
  },
  {
    "nhs": "9541088074",
    "name": "Kendricks Budgey",
    "doctor": "Dr. Noak Kyrkeman",
    "doctorEmail": "nkyrkeman3@foxnews.com",
    "doctorId": 4,
    "patientEmail": "kbudgeyx@sohu.com",
    "items": [
      {
        "date": "2025-11-27",
        "time": "15:30",
        "type": "General Check-up",
        "desc": "Routine health screening and vitals",
        "doctorEmail": "nkyrkeman3@foxnews.com",
        "doctorId": 4
      },
      {
        "date": "2026-11-16",
        "time": "11:00",
        "type": "Dermatology",
        "desc": "Skin inspection and treatment planning",
        "doctorEmail": "mcaghy5@surveymonkey.com",
        "doctorId": 6
      }
    ]
  },
  {
    "nhs": "6471828837",
    "name": "Jeremiah Monnoyer",
    "doctor": "Dr. Rad Philipard",
    "doctorEmail": "rphilipard6@mayoclinic.com",
    "doctorId": 7,
    "patientEmail": "jmonnoyery@parallels.com",
    "items": [
      {
        "date": "2026-08-28",
        "time": "09:45",
        "type": "Physiotherapy",
        "desc": "Mobility, pain and exercise plan",
        "doctorEmail": "rphilipard6@mayoclinic.com",
        "doctorId": 7
      },
      {
        "date": "2026-09-09",
        "time": "16:45",
        "type": "Physiotherapy",
        "desc": "Mobility, pain and exercise plan",
        "doctorEmail": "rblount8@pen.io",
        "doctorId": 9
      }
    ]
  },
  {
    "nhs": "4176305606",
    "name": "Iormina Fiddy",
    "doctor": "Dr. Irvin Dumberrill",
    "doctorEmail": "idumberrilld@toplist.cz",
    "doctorId": 14,
    "patientEmail": "ifiddyz@gravatar.com",
    "items": [
      {
        "date": "2026-10-06",
        "time": "13:30",
        "type": "Diabetes Review",
        "desc": "HbA1c review, medication and diet",
        "doctorEmail": "idumberrilld@toplist.cz",
        "doctorId": 14
      },
      {
        "date": "2026-10-14",
        "time": "16:15",
        "type": "Dental Cleaning",
        "desc": "Teeth cleaning and cavity inspection",
        "doctorEmail": "ebeardsworth1@mac.com",
        "doctorId": 2
      }
    ]
  },
  {
    "nhs": "7586577323",
    "name": "Gabby O'Fogarty",
    "doctor": "Dr. Merrily Harmson",
    "doctorEmail": "mharmsona@i2i.jp",
    "doctorId": 11,
    "patientEmail": "gofogarty10@msn.com",
    "items": [
      {
        "date": "2026-03-02",
        "time": "16:15",
        "type": "Physiotherapy",
        "desc": "Mobility, pain and exercise plan",
        "doctorEmail": "mharmsona@i2i.jp",
        "doctorId": 11
      },
      {
        "date": "2026-08-23",
        "time": "10:15",
        "type": "General Check-up",
        "desc": "Routine health screening and vitals",
        "doctorEmail": "emcquillan2@about.me",
        "doctorId": 3
      },
      {
        "date": "2026-11-03",
        "time": "08:15",
        "type": "Follow-up",
        "desc": "Review of recent results and symptoms",
        "doctorEmail": "mharmsona@i2i.jp",
        "doctorId": 11
      }
    ]
  },
  {
    "nhs": "6203338710",
    "name": "Agathe Dalyiel",
    "doctor": "Dr. Ettie Beardsworth",
    "doctorEmail": "ebeardsworth1@mac.com",
    "doctorId": 2,
    "patientEmail": "adalyiel11@statcounter.com",
    "items": [
      {
        "date": "2026-03-21",
        "time": "16:00",
        "type": "Dermatology",
        "desc": "Skin inspection and treatment planning",
        "doctorEmail": "ebeardsworth1@mac.com",
        "doctorId": 2
      },
      {
        "date": "2026-04-12",
        "time": "15:00",
        "type": "Vaccination",
        "desc": "Routine immunization booster",
        "doctorEmail": "sgivese@wsj.com",
        "doctorId": 15
      }
    ]
  },
  {
    "nhs": "1455229172",
    "name": "Flossi Gobbet",
    "doctor": "Dr. Irvin Dumberrill",
    "doctorEmail": "idumberrilld@toplist.cz",
    "doctorId": 14,
    "patientEmail": "fgobbet12@facebook.com",
    "items": [
      {
        "date": "2025-11-30",
        "time": "13:15",
        "type": "Pediatrics",
        "desc": "Child growth, vaccination and development",
        "doctorEmail": "idumberrilld@toplist.cz",
        "doctorId": 14
      },
      {
        "date": "2026-06-25",
        "time": "11:45",
        "type": "Ophthalmology",
        "desc": "Vision assessment and lens/eye health",
        "doctorEmail": "sgivese@wsj.com",
        "doctorId": 15
      },
      {
        "date": "2026-09-23",
        "time": "08:15",
        "type": "Pediatrics",
        "desc": "Child growth, vaccination and development",
        "doctorEmail": "spawling9@princeton.edu",
        "doctorId": 10
      }
    ]
  },
  {
    "nhs": "4607334987",
    "name": "Osmond Ochterlony",
    "doctor": "Dr. Irvin Dumberrill",
    "doctorEmail": "idumberrilld@toplist.cz",
    "doctorId": 14,
    "patientEmail": "oochterlony13@comsenz.com",
    "items": [
      {
        "date": "2026-11-13",
        "time": "15:30",
        "type": "Neurology",
        "desc": "Headache, dizziness and neuro exam",
        "doctorEmail": "idumberrilld@toplist.cz",
        "doctorId": 14
      },
      {
        "date": "2026-12-01",
        "time": "13:00",
        "type": "Dermatology",
        "desc": "Skin inspection and treatment planning",
        "doctorEmail": "idumberrilld@toplist.cz",
        "doctorId": 14
      }
    ]
  },
  {
    "nhs": "4920143451",
    "name": "Hector Beringer",
    "doctor": "Dr. Emera McQuillan",
    "doctorEmail": "emcquillan2@about.me",
    "doctorId": 3,
    "patientEmail": "hberinger14@desdev.cn",
    "items": [
      {
        "date": "2026-03-11",
        "time": "13:15",
        "type": "General Check-up",
        "desc": "Routine health screening and vitals",
        "doctorEmail": "emcquillan2@about.me",
        "doctorId": 3
      },
      {
        "date": "2026-09-23",
        "time": "11:15",
        "type": "Cardiology Consultation",
        "desc": "Discuss chest discomfort and risk factors",
        "doctorEmail": "nkyrkeman3@foxnews.com",
        "doctorId": 4
      }
    ]
  },
  {
    "nhs": "5679629224",
    "name": "Patrick Bisset",
    "doctor": "Dr. Irvin Dumberrill",
    "doctorEmail": "idumberrilld@toplist.cz",
    "doctorId": 14,
    "patientEmail": "pbisset15@ed.gov",
    "items": [
      {
        "date": "2025-12-17",
        "time": "16:15",
        "type": "General Check-up",
        "desc": "Routine health screening and vitals",
        "doctorEmail": "idumberrilld@toplist.cz",
        "doctorId": 14
      },
      {
        "date": "2026-02-05",
        "time": "14:00",
        "type": "Ophthalmology",
        "desc": "Vision assessment and lens/eye health",
        "doctorEmail": "emcquillan2@about.me",
        "doctorId": 3
      }
    ]
  },
  {
    "nhs": "6664789957",
    "name": "Glennie Fonquernie",
    "doctor": "Dr. Rowland Blount",
    "doctorEmail": "rblount8@pen.io",
    "doctorId": 9,
    "patientEmail": "gfonquernie16@spotify.com",
    "items": [
      {
        "date": "2026-06-16",
        "time": "12:30",
        "type": "Follow-up",
        "desc": "Review of recent results and symptoms",
        "doctorEmail": "rblount8@pen.io",
        "doctorId": 9
      },
      {
        "date": "2026-09-05",
        "time": "10:00",
        "type": "Hypertension Review",
        "desc": "BP trend review and medication",
        "doctorEmail": "mcaghy5@surveymonkey.com",
        "doctorId": 6
      }
    ]
  },
  {
    "nhs": "3137478995",
    "name": "Toma McConway",
    "doctor": "Dr. Erwin Handlin",
    "doctorEmail": "ehandlin4@gravatar.com",
    "doctorId": 5,
    "patientEmail": "tmcconway17@clickbank.net",
    "items": [
      {
        "date": "2026-02-03",
        "time": "11:15",
        "type": "Cardiology Consultation",
        "desc": "Discuss chest discomfort and risk factors",
        "doctorEmail": "ehandlin4@gravatar.com",
        "doctorId": 5
      },
      {
        "date": "2026-03-01",
        "time": "12:30",
        "type": "Hypertension Review",
        "desc": "BP trend review and medication",
        "doctorEmail": "rblount8@pen.io",
        "doctorId": 9
      },
      {
        "date": "2026-09-04",
        "time": "08:30",
        "type": "Orthopedics",
        "desc": "Joint/muscle pain assessment",
        "doctorEmail": "nkyrkeman3@foxnews.com",
        "doctorId": 4
      }
    ]
  },
  {
    "nhs": "5456734834",
    "name": "Anthea Abrahamsen",
    "doctor": "Dr. Noak Kyrkeman",
    "doctorEmail": "nkyrkeman3@foxnews.com",
    "doctorId": 4,
    "patientEmail": "aabrahamsen18@photobucket.com",
    "items": [
      {
        "date": "2026-06-05",
        "time": "16:00",
        "type": "General Check-up",
        "desc": "Routine health screening and vitals",
        "doctorEmail": "nkyrkeman3@foxnews.com",
        "doctorId": 4
      },
      {
        "date": "2026-08-18",
        "time": "10:00",
        "type": "Vaccination",
        "desc": "Routine immunization booster",
        "doctorEmail": "zgalloway7@ca.gov",
        "doctorId": 8
      },
      {
        "date": "2026-12-26",
        "time": "10:45",
        "type": "Cardiology Consultation",
        "desc": "Discuss chest discomfort and risk factors",
        "doctorEmail": "spawling9@princeton.edu",
        "doctorId": 10
      }
    ]
  },
  {
    "nhs": "9046839311",
    "name": "Bianca Kindleysides",
    "doctor": "Dr. Cordell Toor",
    "doctorEmail": "ctoorb@psu.edu",
    "doctorId": 12,
    "patientEmail": "bkindleysides19@google.co.jp",
    "items": [
      {
        "date": "2026-03-29",
        "time": "15:00",
        "type": "Dermatology",
        "desc": "Skin inspection and treatment planning",
        "doctorEmail": "ctoorb@psu.edu",
        "doctorId": 12
      },
      {
        "date": "2026-04-05",
        "time": "15:45",
        "type": "Follow-up",
        "desc": "Review of recent results and symptoms",
        "doctorEmail": "zgalloway7@ca.gov",
        "doctorId": 8
      },
      {
        "date": "2026-11-15",
        "time": "08:45",
        "type": "Cardiology Consultation",
        "desc": "Discuss chest discomfort and risk factors",
        "doctorEmail": "vrilton0@discuz.net",
        "doctorId": 1
      }
    ]
  },
  {
    "nhs": "2029708895",
    "name": "Zelda Caughte",
    "doctor": "Dr. Violante Rilton",
    "doctorEmail": "vrilton0@discuz.net",
    "doctorId": 1,
    "patientEmail": "zcaughte1a@pinterest.com",
    "items": [
      {
        "date": "2025-12-05",
        "time": "10:30",
        "type": "Ophthalmology",
        "desc": "Vision assessment and lens/eye health",
        "doctorEmail": "vrilton0@discuz.net",
        "doctorId": 1
      },
      {
        "date": "2026-11-23",
        "time": "10:30",
        "type": "Follow-up",
        "desc": "Review of recent results and symptoms",
        "doctorEmail": "ehandlin4@gravatar.com",
        "doctorId": 5
      }
    ]
  },
  {
    "nhs": "9253511109",
    "name": "Beryle Christoffels",
    "doctor": "Dr. Rad Philipard",
    "doctorEmail": "rphilipard6@mayoclinic.com",
    "doctorId": 7,
    "patientEmail": "bchristoffels1b@twitpic.com",
    "items": [
      {
        "date": "2025-12-07",
        "time": "08:00",
        "type": "Physiotherapy",
        "desc": "Mobility, pain and exercise plan",
        "doctorEmail": "rphilipard6@mayoclinic.com",
        "doctorId": 7
      },
      {
        "date": "2026-12-12",
        "time": "11:45",
        "type": "Cardiology Consultation",
        "desc": "Discuss chest discomfort and risk factors",
        "doctorEmail": "mharmsona@i2i.jp",
        "doctorId": 11
      }
    ]
  },
  {
    "nhs": "6034202965",
    "name": "Mort Abramovic",
    "doctor": "Dr. Monah Caghy",
    "doctorEmail": "mcaghy5@surveymonkey.com",
    "doctorId": 6,
    "patientEmail": "mabramovic1c@technorati.com",
    "items": [
      {
        "date": "2026-02-03",
        "time": "09:15",
        "type": "Follow-up",
        "desc": "Review of recent results and symptoms",
        "doctorEmail": "mcaghy5@surveymonkey.com",
        "doctorId": 6
      },
      {
        "date": "2026-05-30",
        "time": "13:00",
        "type": "Physiotherapy",
        "desc": "Mobility, pain and exercise plan",
        "doctorEmail": "rphilipard6@mayoclinic.com",
        "doctorId": 7
      }
    ]
  },
  {
    "nhs": "0667088997",
    "name": "Tedmund Cutchee",
    "doctor": "Dr. Monah Caghy",
    "doctorEmail": "mcaghy5@surveymonkey.com",
    "doctorId": 6,
    "patientEmail": "tcutchee1d@nih.gov",
    "items": [
      {
        "date": "2025-12-16",
        "time": "15:45",
        "type": "General Check-up",
        "desc": "Routine health screening and vitals",
        "doctorEmail": "mcaghy5@surveymonkey.com",
        "doctorId": 6
      },
      {
        "date": "2026-07-18",
        "time": "11:00",
        "type": "Diabetes Review",
        "desc": "HbA1c review, medication and diet",
        "doctorEmail": "mcaghy5@surveymonkey.com",
        "doctorId": 6
      },
      {
        "date": "2026-11-17",
        "time": "16:30",
        "type": "Neurology",
        "desc": "Headache, dizziness and neuro exam",
        "doctorEmail": "rphilipard6@mayoclinic.com",
        "doctorId": 7
      }
    ]
  },
  {
    "nhs": "3852507189",
    "name": "Shirley Lipsett",
    "doctor": "Dr. Erwin Handlin",
    "doctorEmail": "ehandlin4@gravatar.com",
    "doctorId": 5,
    "patientEmail": "slipsett1e@ameblo.jp",
    "items": [
      {
        "date": "2026-07-22",
        "time": "14:00",
        "type": "Physiotherapy",
        "desc": "Mobility, pain and exercise plan",
        "doctorEmail": "ehandlin4@gravatar.com",
        "doctorId": 5
      },
      {
        "date": "2026-12-29",
        "time": "12:15",
        "type": "Physiotherapy",
        "desc": "Mobility, pain and exercise plan",
        "doctorEmail": "ctoorb@psu.edu",
        "doctorId": 12
      }
    ]
  },
  {
    "nhs": "7547043135",
    "name": "Sawyer Hughlock",
    "doctor": "Dr. Irvin Dumberrill",
    "doctorEmail": "idumberrilld@toplist.cz",
    "doctorId": 14,
    "patientEmail": "shughlock1f@ifeng.com",
    "items": [
      {
        "date": "2026-03-12",
        "time": "09:30",
        "type": "ENT Examination",
        "desc": "Ear, nose and throat review",
        "doctorEmail": "idumberrilld@toplist.cz",
        "doctorId": 14
      },
      {
        "date": "2026-05-14",
        "time": "09:45",
        "type": "Vaccination",
        "desc": "Routine immunization booster",
        "doctorEmail": "mcaghy5@surveymonkey.com",
        "doctorId": 6
      },
      {
        "date": "2026-05-22",
        "time": "15:30",
        "type": "General Check-up",
        "desc": "Routine health screening and vitals",
        "doctorEmail": "ebeardsworth1@mac.com",
        "doctorId": 2
      }
    ]
  },
  {
    "nhs": "9880383567",
    "name": "Leilah Willgrass",
    "doctor": "Dr. Emera McQuillan",
    "doctorEmail": "emcquillan2@about.me",
    "doctorId": 3,
    "patientEmail": "lwillgrass1g@webs.com",
    "items": [
      {
        "date": "2026-05-04",
        "time": "15:45",
        "type": "Pediatrics",
        "desc": "Child growth, vaccination and development",
        "doctorEmail": "emcquillan2@about.me",
        "doctorId": 3
      },
      {
        "date": "2026-12-05",
        "time": "14:45",
        "type": "Orthopedics",
        "desc": "Joint/muscle pain assessment",
        "doctorEmail": "hwillingamc@springer.com",
        "doctorId": 13
      },
      {
        "date": "2026-12-15",
        "time": "15:30",
        "type": "Cardiology Consultation",
        "desc": "Discuss chest discomfort and risk factors",
        "doctorEmail": "zgalloway7@ca.gov",
        "doctorId": 8
      }
    ]
  },
  {
    "nhs": "4976220591",
    "name": "Chantalle Tweede",
    "doctor": "Dr. Cordell Toor",
    "doctorEmail": "ctoorb@psu.edu",
    "doctorId": 12,
    "patientEmail": "ctweede1h@sun.com",
    "items": [
      {
        "date": "2026-02-04",
        "time": "11:00",
        "type": "Physiotherapy",
        "desc": "Mobility, pain and exercise plan",
        "doctorEmail": "ctoorb@psu.edu",
        "doctorId": 12
      },
      {
        "date": "2026-05-02",
        "time": "08:45",
        "type": "Dental Cleaning",
        "desc": "Teeth cleaning and cavity inspection",
        "doctorEmail": "mcaghy5@surveymonkey.com",
        "doctorId": 6
      },
      {
        "date": "2026-06-05",
        "time": "09:30",
        "type": "Follow-up",
        "desc": "Review of recent results and symptoms",
        "doctorEmail": "ehandlin4@gravatar.com",
        "doctorId": 5
      }
    ]
  },
  {
    "nhs": "0901893994",
    "name": "Emmerich Roubottom",
    "doctor": "Dr. Merrily Harmson",
    "doctorEmail": "mharmsona@i2i.jp",
    "doctorId": 11,
    "patientEmail": "eroubottom1i@addthis.com",
    "items": [
      {
        "date": "2026-02-28",
        "time": "11:00",
        "type": "Hypertension Review",
        "desc": "BP trend review and medication",
        "doctorEmail": "mharmsona@i2i.jp",
        "doctorId": 11
      },
      {
        "date": "2026-11-20",
        "time": "08:45",
        "type": "Pediatrics",
        "desc": "Child growth, vaccination and development",
        "doctorEmail": "zgalloway7@ca.gov",
        "doctorId": 8
      },
      {
        "date": "2026-12-10",
        "time": "12:00",
        "type": "Neurology",
        "desc": "Headache, dizziness and neuro exam",
        "doctorEmail": "idumberrilld@toplist.cz",
        "doctorId": 14
      }
    ]
  },
  {
    "nhs": "0689695497",
    "name": "Sandy Flahy",
    "doctor": "Dr. Irvin Dumberrill",
    "doctorEmail": "idumberrilld@toplist.cz",
    "doctorId": 14,
    "patientEmail": "sflahy1j@cyberchimps.com",
    "items": [
      {
        "date": "2025-12-26",
        "time": "15:45",
        "type": "Ophthalmology",
        "desc": "Vision assessment and lens/eye health",
        "doctorEmail": "idumberrilld@toplist.cz",
        "doctorId": 14
      },
      {
        "date": "2026-06-22",
        "time": "12:45",
        "type": "Orthopedics",
        "desc": "Joint/muscle pain assessment",
        "doctorEmail": "spawling9@princeton.edu",
        "doctorId": 10
      },
      {
        "date": "2026-09-19",
        "time": "13:45",
        "type": "Diabetes Review",
        "desc": "HbA1c review, medication and diet",
        "doctorEmail": "vrilton0@discuz.net",
        "doctorId": 1
      }
    ]
  },
  {
    "nhs": "7516975605",
    "name": "Elane O'Cuddie",
    "doctor": "Dr. Emera McQuillan",
    "doctorEmail": "emcquillan2@about.me",
    "doctorId": 3,
    "patientEmail": "eocuddie1k@prlog.org",
    "items": [
      {
        "date": "2026-04-26",
        "time": "10:45",
        "type": "Pediatrics",
        "desc": "Child growth, vaccination and development",
        "doctorEmail": "emcquillan2@about.me",
        "doctorId": 3
      },
      {
        "date": "2026-09-15",
        "time": "11:15",
        "type": "Vaccination",
        "desc": "Routine immunization booster",
        "doctorEmail": "spawling9@princeton.edu",
        "doctorId": 10
      },
      {
        "date": "2026-11-12",
        "time": "12:30",
        "type": "Hypertension Review",
        "desc": "BP trend review and medication",
        "doctorEmail": "ebeardsworth1@mac.com",
        "doctorId": 2
      }
    ]
  },
  {
    "nhs": "5383430830",
    "name": "Minnie Durbann",
    "doctor": "Dr. Erwin Handlin",
    "doctorEmail": "ehandlin4@gravatar.com",
    "doctorId": 5,
    "patientEmail": "mdurbann1l@dailymotion.com",
    "items": [
      {
        "date": "2026-06-11",
        "time": "08:45",
        "type": "Dermatology",
        "desc": "Skin inspection and treatment planning",
        "doctorEmail": "ehandlin4@gravatar.com",
        "doctorId": 5
      },
      {
        "date": "2026-07-23",
        "time": "12:45",
        "type": "Dermatology",
        "desc": "Skin inspection and treatment planning",
        "doctorEmail": "nkyrkeman3@foxnews.com",
        "doctorId": 4
      }
    ]
  },
  {
    "nhs": "7494744711",
    "name": "De witt Ayllett",
    "doctor": "Dr. Merrily Harmson",
    "doctorEmail": "mharmsona@i2i.jp",
    "doctorId": 11,
    "patientEmail": "dayllett1m@unesco.org",
    "items": [
      {
        "date": "2025-11-20",
        "time": "15:00",
        "type": "ENT Examination",
        "desc": "Ear, nose and throat review",
        "doctorEmail": "mharmsona@i2i.jp",
        "doctorId": 11
      },
      {
        "date": "2026-03-16",
        "time": "14:15",
        "type": "Follow-up",
        "desc": "Review of recent results and symptoms",
        "doctorEmail": "mcaghy5@surveymonkey.com",
        "doctorId": 6
      }
    ]
  },
  {
    "nhs": "5353682432",
    "name": "Victor Hartnell",
    "doctor": "Dr. Rad Philipard",
    "doctorEmail": "rphilipard6@mayoclinic.com",
    "doctorId": 7,
    "patientEmail": "vhartnell1n@edublogs.org",
    "items": [
      {
        "date": "2025-11-25",
        "time": "16:30",
        "type": "Orthopedics",
        "desc": "Joint/muscle pain assessment",
        "doctorEmail": "rphilipard6@mayoclinic.com",
        "doctorId": 7
      },
      {
        "date": "2026-05-25",
        "time": "11:15",
        "type": "Dental Cleaning",
        "desc": "Teeth cleaning and cavity inspection",
        "doctorEmail": "zgalloway7@ca.gov",
        "doctorId": 8
      }
    ]
  },
  {
    "nhs": "0379517825",
    "name": "Neddy Marrion",
    "doctor": "Dr. Ettie Beardsworth",
    "doctorEmail": "ebeardsworth1@mac.com",
    "doctorId": 2,
    "patientEmail": "nmarrion1o@dion.ne.jp",
    "items": [
      {
        "date": "2026-02-11",
        "time": "10:30",
        "type": "Orthopedics",
        "desc": "Joint/muscle pain assessment",
        "doctorEmail": "ebeardsworth1@mac.com",
        "doctorId": 2
      },
      {
        "date": "2026-09-12",
        "time": "13:15",
        "type": "Dental Cleaning",
        "desc": "Teeth cleaning and cavity inspection",
        "doctorEmail": "nkyrkeman3@foxnews.com",
        "doctorId": 4
      }
    ]
  },
  {
    "nhs": "1230322833",
    "name": "Robert Neve",
    "doctor": "Dr. Erwin Handlin",
    "doctorEmail": "ehandlin4@gravatar.com",
    "doctorId": 5,
    "patientEmail": "rneve1p@goo.ne.jp",
    "items": [
      {
        "date": "2025-12-22",
        "time": "15:15",
        "type": "Neurology",
        "desc": "Headache, dizziness and neuro exam",
        "doctorEmail": "ehandlin4@gravatar.com",
        "doctorId": 5
      },
      {
        "date": "2026-03-12",
        "time": "10:15",
        "type": "Physiotherapy",
        "desc": "Mobility, pain and exercise plan",
        "doctorEmail": "nkyrkeman3@foxnews.com",
        "doctorId": 4
      },
      {
        "date": "2026-09-07",
        "time": "15:45",
        "type": "Dermatology",
        "desc": "Skin inspection and treatment planning",
        "doctorEmail": "emcquillan2@about.me",
        "doctorId": 3
      }
    ]
  },
  {
    "nhs": "9252211462",
    "name": "Eward Bromilow",
    "doctor": "Dr. Cordell Toor",
    "doctorEmail": "ctoorb@psu.edu",
    "doctorId": 12,
    "patientEmail": "ebromilow1q@utexas.edu",
    "items": [
      {
        "date": "2026-02-24",
        "time": "11:15",
        "type": "General Check-up",
        "desc": "Routine health screening and vitals",
        "doctorEmail": "ctoorb@psu.edu",
        "doctorId": 12
      },
      {
        "date": "2026-04-11",
        "time": "12:00",
        "type": "Physiotherapy",
        "desc": "Mobility, pain and exercise plan",
        "doctorEmail": "rphilipard6@mayoclinic.com",
        "doctorId": 7
      }
    ]
  },
  {
    "nhs": "2296156193",
    "name": "Ronny Ganforthe",
    "doctor": "Dr. Violante Rilton",
    "doctorEmail": "vrilton0@discuz.net",
    "doctorId": 1,
    "patientEmail": "rganforthe1r@surveymonkey.com",
    "items": [
      {
        "date": "2025-12-02",
        "time": "09:15",
        "type": "Follow-up",
        "desc": "Review of recent results and symptoms",
        "doctorEmail": "vrilton0@discuz.net",
        "doctorId": 1
      },
      {
        "date": "2026-07-16",
        "time": "13:00",
        "type": "Hypertension Review",
        "desc": "BP trend review and medication",
        "doctorEmail": "hwillingamc@springer.com",
        "doctorId": 13
      },
      {
        "date": "2026-08-16",
        "time": "14:30",
        "type": "ENT Examination",
        "desc": "Ear, nose and throat review",
        "doctorEmail": "zgalloway7@ca.gov",
        "doctorId": 8
      }
    ]
  },
  {
    "nhs": "1575207966",
    "name": "Carlene Ravel",
    "doctor": "Dr. Monah Caghy",
    "doctorEmail": "mcaghy5@surveymonkey.com",
    "doctorId": 6,
    "patientEmail": "cravel1s@theguardian.com",
    "items": [
      {
        "date": "2026-01-27",
        "time": "11:30",
        "type": "General Check-up",
        "desc": "Routine health screening and vitals",
        "doctorEmail": "mcaghy5@surveymonkey.com",
        "doctorId": 6
      },
      {
        "date": "2026-05-19",
        "time": "10:30",
        "type": "ENT Examination",
        "desc": "Ear, nose and throat review",
        "doctorEmail": "ehandlin4@gravatar.com",
        "doctorId": 5
      },
      {
        "date": "2026-10-08",
        "time": "16:30",
        "type": "ENT Examination",
        "desc": "Ear, nose and throat review",
        "doctorEmail": "ebeardsworth1@mac.com",
        "doctorId": 2
      }
    ]
  },
  {
    "nhs": "9231682180",
    "name": "Harley Powys",
    "doctor": "Dr. Noak Kyrkeman",
    "doctorEmail": "nkyrkeman3@foxnews.com",
    "doctorId": 4,
    "patientEmail": "hpowys1t@wikispaces.com",
    "items": [
      {
        "date": "2026-01-09",
        "time": "16:30",
        "type": "Diabetes Review",
        "desc": "HbA1c review, medication and diet",
        "doctorEmail": "nkyrkeman3@foxnews.com",
        "doctorId": 4
      },
      {
        "date": "2026-03-09",
        "time": "09:15",
        "type": "Physiotherapy",
        "desc": "Mobility, pain and exercise plan",
        "doctorEmail": "zgalloway7@ca.gov",
        "doctorId": 8
      }
    ]
  },
  {
    "nhs": "7059121684",
    "name": "Konstantin Lowles",
    "doctor": "Dr. Emera McQuillan",
    "doctorEmail": "emcquillan2@about.me",
    "doctorId": 3,
    "patientEmail": "klowles1u@amazon.de",
    "items": [
      {
        "date": "2025-11-06",
        "time": "16:45",
        "type": "Physiotherapy",
        "desc": "Mobility, pain and exercise plan",
        "doctorEmail": "emcquillan2@about.me",
        "doctorId": 3
      },
      {
        "date": "2025-11-18",
        "time": "11:00",
        "type": "Pediatrics",
        "desc": "Child growth, vaccination and development",
        "doctorEmail": "ctoorb@psu.edu",
        "doctorId": 12
      },
      {
        "date": "2026-03-25",
        "time": "16:30",
        "type": "Dental Cleaning",
        "desc": "Teeth cleaning and cavity inspection",
        "doctorEmail": "spawling9@princeton.edu",
        "doctorId": 10
      }
    ]
  },
  {
    "nhs": "0117253944",
    "name": "Vina Mordanti",
    "doctor": "Dr. Irvin Dumberrill",
    "doctorEmail": "idumberrilld@toplist.cz",
    "doctorId": 14,
    "patientEmail": "vmordanti1v@hexun.com",
    "items": [
      {
        "date": "2026-01-18",
        "time": "09:45",
        "type": "Cardiology Consultation",
        "desc": "Discuss chest discomfort and risk factors",
        "doctorEmail": "idumberrilld@toplist.cz",
        "doctorId": 14
      },
      {
        "date": "2026-03-06",
        "time": "15:00",
        "type": "Dermatology",
        "desc": "Skin inspection and treatment planning",
        "doctorEmail": "mcaghy5@surveymonkey.com",
        "doctorId": 6
      }
    ]
  },
  {
    "nhs": "8549714305",
    "name": "Guglielmo Seabrocke",
    "doctor": "Dr. Ettie Beardsworth",
    "doctorEmail": "ebeardsworth1@mac.com",
    "doctorId": 2,
    "patientEmail": "gseabrocke1w@unicef.org",
    "items": [
      {
        "date": "2026-02-20",
        "time": "09:30",
        "type": "Vaccination",
        "desc": "Routine immunization booster",
        "doctorEmail": "ebeardsworth1@mac.com",
        "doctorId": 2
      },
      {
        "date": "2026-08-24",
        "time": "11:30",
        "type": "Orthopedics",
        "desc": "Joint/muscle pain assessment",
        "doctorEmail": "rblount8@pen.io",
        "doctorId": 9
      }
    ]
  },
  {
    "nhs": "5663733841",
    "name": "Vera Hubbins",
    "doctor": "Dr. Rad Philipard",
    "doctorEmail": "rphilipard6@mayoclinic.com",
    "doctorId": 7,
    "patientEmail": "vhubbins1x@ocn.ne.jp",
    "items": [
      {
        "date": "2026-02-12",
        "time": "10:15",
        "type": "Orthopedics",
        "desc": "Joint/muscle pain assessment",
        "doctorEmail": "rphilipard6@mayoclinic.com",
        "doctorId": 7
      },
      {
        "date": "2026-11-01",
        "time": "09:30",
        "type": "Physiotherapy",
        "desc": "Mobility, pain and exercise plan",
        "doctorEmail": "vrilton0@discuz.net",
        "doctorId": 1
      }
    ]
  },
  {
    "nhs": "8201426894",
    "name": "Wittie Corney",
    "doctor": "Dr. Rowland Blount",
    "doctorEmail": "rblount8@pen.io",
    "doctorId": 9,
    "patientEmail": "wcorney1y@alibaba.com",
    "items": [
      {
        "date": "2025-11-07",
        "time": "14:45",
        "type": "Orthopedics",
        "desc": "Joint/muscle pain assessment",
        "doctorEmail": "rblount8@pen.io",
        "doctorId": 9
      },
      {
        "date": "2026-07-06",
        "time": "13:00",
        "type": "Diabetes Review",
        "desc": "HbA1c review, medication and diet",
        "doctorEmail": "emcquillan2@about.me",
        "doctorId": 3
      },
      {
        "date": "2026-08-04",
        "time": "12:15",
        "type": "Physiotherapy",
        "desc": "Mobility, pain and exercise plan",
        "doctorEmail": "mharmsona@i2i.jp",
        "doctorId": 11
      }
    ]
  },
  {
    "nhs": "4334743129",
    "name": "Chelsy Schwand",
    "doctor": "Dr. Erwin Handlin",
    "doctorEmail": "ehandlin4@gravatar.com",
    "doctorId": 5,
    "patientEmail": "cschwand1z@mtv.com",
    "items": [
      {
        "date": "2026-10-08",
        "time": "11:45",
        "type": "Pediatrics",
        "desc": "Child growth, vaccination and development",
        "doctorEmail": "ehandlin4@gravatar.com",
        "doctorId": 5
      },
      {
        "date": "2026-12-11",
        "time": "13:00",
        "type": "ENT Examination",
        "desc": "Ear, nose and throat review",
        "doctorEmail": "rblount8@pen.io",
        "doctorId": 9
      }
    ]
  },
  {
    "nhs": "2014021686",
    "name": "Kevyn Kilshaw",
    "doctor": "Dr. Si Pawling",
    "doctorEmail": "spawling9@princeton.edu",
    "doctorId": 10,
    "patientEmail": "kkilshaw20@google.ru",
    "items": [
      {
        "date": "2026-01-15",
        "time": "09:30",
        "type": "General Check-up",
        "desc": "Routine health screening and vitals",
        "doctorEmail": "spawling9@princeton.edu",
        "doctorId": 10
      },
      {
        "date": "2026-04-17",
        "time": "13:00",
        "type": "Dermatology",
        "desc": "Skin inspection and treatment planning",
        "doctorEmail": "ebeardsworth1@mac.com",
        "doctorId": 2
      },
      {
        "date": "2026-05-23",
        "time": "14:15",
        "type": "Pediatrics",
        "desc": "Child growth, vaccination and development",
        "doctorEmail": "spawling9@princeton.edu",
        "doctorId": 10
      }
    ]
  },
  {
    "nhs": "2525930002",
    "name": "Crissy Keave",
    "doctor": "Dr. Violante Rilton",
    "doctorEmail": "vrilton0@discuz.net",
    "doctorId": 1,
    "patientEmail": "ckeave21@youtube.com",
    "items": [
      {
        "date": "2026-04-13",
        "time": "12:30",
        "type": "Neurology",
        "desc": "Headache, dizziness and neuro exam",
        "doctorEmail": "vrilton0@discuz.net",
        "doctorId": 1
      },
      {
        "date": "2026-11-18",
        "time": "16:00",
        "type": "Physiotherapy",
        "desc": "Mobility, pain and exercise plan",
        "doctorEmail": "ebeardsworth1@mac.com",
        "doctorId": 2
      }
    ]
  },
  {
    "nhs": "9385343513",
    "name": "North Allright",
    "doctor": "Dr. Ettie Beardsworth",
    "doctorEmail": "ebeardsworth1@mac.com",
    "doctorId": 2,
    "patientEmail": "nallright22@forbes.com",
    "items": [
      {
        "date": "2025-12-29",
        "time": "09:15",
        "type": "Cardiology Consultation",
        "desc": "Discuss chest discomfort and risk factors",
        "doctorEmail": "ebeardsworth1@mac.com",
        "doctorId": 2
      },
      {
        "date": "2026-10-18",
        "time": "09:30",
        "type": "Hypertension Review",
        "desc": "BP trend review and medication",
        "doctorEmail": "rblount8@pen.io",
        "doctorId": 9
      }
    ]
  },
  {
    "nhs": "0083453962",
    "name": "Alissa Claiden",
    "doctor": "Dr. Erwin Handlin",
    "doctorEmail": "ehandlin4@gravatar.com",
    "doctorId": 5,
    "patientEmail": "aclaiden23@geocities.com",
    "items": [
      {
        "date": "2026-01-11",
        "time": "13:30",
        "type": "ENT Examination",
        "desc": "Ear, nose and throat review",
        "doctorEmail": "ehandlin4@gravatar.com",
        "doctorId": 5
      },
      {
        "date": "2026-12-20",
        "time": "14:00",
        "type": "Follow-up",
        "desc": "Review of recent results and symptoms",
        "doctorEmail": "ebeardsworth1@mac.com",
        "doctorId": 2
      },
      {
        "date": "2026-12-31",
        "time": "08:30",
        "type": "Neurology",
        "desc": "Headache, dizziness and neuro exam",
        "doctorEmail": "ctoorb@psu.edu",
        "doctorId": 12
      }
    ]
  },
  {
    "nhs": "5892205592",
    "name": "Mac Kerr",
    "doctor": "Dr. Erwin Handlin",
    "doctorEmail": "ehandlin4@gravatar.com",
    "doctorId": 5,
    "patientEmail": "mkerr24@senate.gov",
    "items": [
      {
        "date": "2026-03-25",
        "time": "13:15",
        "type": "ENT Examination",
        "desc": "Ear, nose and throat review",
        "doctorEmail": "ehandlin4@gravatar.com",
        "doctorId": 5
      },
      {
        "date": "2026-05-06",
        "time": "10:45",
        "type": "Vaccination",
        "desc": "Routine immunization booster",
        "doctorEmail": "mharmsona@i2i.jp",
        "doctorId": 11
      },
      {
        "date": "2026-08-19",
        "time": "09:30",
        "type": "Diabetes Review",
        "desc": "HbA1c review, medication and diet",
        "doctorEmail": "ctoorb@psu.edu",
        "doctorId": 12
      }
    ]
  },
  {
    "nhs": "6010203082",
    "name": "Jennica Echallie",
    "doctor": "Dr. Irvin Dumberrill",
    "doctorEmail": "idumberrilld@toplist.cz",
    "doctorId": 14,
    "patientEmail": "jechallie25@angelfire.com",
    "items": [
      {
        "date": "2025-12-21",
        "time": "11:00",
        "type": "Orthopedics",
        "desc": "Joint/muscle pain assessment",
        "doctorEmail": "idumberrilld@toplist.cz",
        "doctorId": 14
      },
      {
        "date": "2026-04-20",
        "time": "11:45",
        "type": "Vaccination",
        "desc": "Routine immunization booster",
        "doctorEmail": "ebeardsworth1@mac.com",
        "doctorId": 2
      },
      {
        "date": "2026-07-21",
        "time": "09:00",
        "type": "Follow-up",
        "desc": "Review of recent results and symptoms",
        "doctorEmail": "ctoorb@psu.edu",
        "doctorId": 12
      }
    ]
  },
  {
    "nhs": "9369147934",
    "name": "Francis Cottrell",
    "doctor": "Dr. Si Pawling",
    "doctorEmail": "spawling9@princeton.edu",
    "doctorId": 10,
    "patientEmail": "fcottrell26@ezinearticles.com",
    "items": [
      {
        "date": "2026-06-27",
        "time": "10:15",
        "type": "Follow-up",
        "desc": "Review of recent results and symptoms",
        "doctorEmail": "spawling9@princeton.edu",
        "doctorId": 10
      },
      {
        "date": "2026-10-28",
        "time": "13:00",
        "type": "Follow-up",
        "desc": "Review of recent results and symptoms",
        "doctorEmail": "spawling9@princeton.edu",
        "doctorId": 10
      }
    ]
  },
  {
    "nhs": "6589057079",
    "name": "Violante Stoker",
    "doctor": "Dr. Erwin Handlin",
    "doctorEmail": "ehandlin4@gravatar.com",
    "doctorId": 5,
    "patientEmail": "vstoker27@over-blog.com",
    "items": [
      {
        "date": "2025-11-20",
        "time": "12:15",
        "type": "Hypertension Review",
        "desc": "BP trend review and medication",
        "doctorEmail": "ehandlin4@gravatar.com",
        "doctorId": 5
      },
      {
        "date": "2026-04-27",
        "time": "15:45",
        "type": "Pediatrics",
        "desc": "Child growth, vaccination and development",
        "doctorEmail": "mcaghy5@surveymonkey.com",
        "doctorId": 6
      },
      {
        "date": "2026-09-09",
        "time": "14:15",
        "type": "ENT Examination",
        "desc": "Ear, nose and throat review",
        "doctorEmail": "rphilipard6@mayoclinic.com",
        "doctorId": 7
      }
    ]
  },
  {
    "nhs": "2936312639",
    "name": "Humfrid Temporal",
    "doctor": "Dr. Si Pawling",
    "doctorEmail": "spawling9@princeton.edu",
    "doctorId": 10,
    "patientEmail": "htemporal28@opera.com",
    "items": [
      {
        "date": "2026-06-07",
        "time": "13:45",
        "type": "Orthopedics",
        "desc": "Joint/muscle pain assessment",
        "doctorEmail": "spawling9@princeton.edu",
        "doctorId": 10
      },
      {
        "date": "2026-09-23",
        "time": "15:30",
        "type": "ENT Examination",
        "desc": "Ear, nose and throat review",
        "doctorEmail": "nkyrkeman3@foxnews.com",
        "doctorId": 4
      }
    ]
  },
  {
    "nhs": "0700059547",
    "name": "Reade Jerisch",
    "doctor": "Dr. Irvin Dumberrill",
    "doctorEmail": "idumberrilld@toplist.cz",
    "doctorId": 14,
    "patientEmail": "rjerisch29@amazonaws.com",
    "items": [
      {
        "date": "2026-06-18",
        "time": "14:15",
        "type": "Diabetes Review",
        "desc": "HbA1c review, medication and diet",
        "doctorEmail": "idumberrilld@toplist.cz",
        "doctorId": 14
      },
      {
        "date": "2026-09-01",
        "time": "14:00",
        "type": "Pediatrics",
        "desc": "Child growth, vaccination and development",
        "doctorEmail": "mharmsona@i2i.jp",
        "doctorId": 11
      },
      {
        "date": "2026-12-11",
        "time": "08:00",
        "type": "Ophthalmology",
        "desc": "Vision assessment and lens/eye health",
        "doctorEmail": "hwillingamc@springer.com",
        "doctorId": 13
      }
    ]
  },
  {
    "nhs": "7113173489",
    "name": "Teodoro Standbrooke",
    "doctor": "Dr. Erwin Handlin",
    "doctorEmail": "ehandlin4@gravatar.com",
    "doctorId": 5,
    "patientEmail": "tstandbrooke2a@earthlink.net",
    "items": [
      {
        "date": "2026-05-01",
        "time": "15:15",
        "type": "Dental Cleaning",
        "desc": "Teeth cleaning and cavity inspection",
        "doctorEmail": "ehandlin4@gravatar.com",
        "doctorId": 5
      },
      {
        "date": "2026-12-05",
        "time": "16:00",
        "type": "Follow-up",
        "desc": "Review of recent results and symptoms",
        "doctorEmail": "hwillingamc@springer.com",
        "doctorId": 13
      }
    ]
  },
  {
    "nhs": "2427976946",
    "name": "Andras Perl",
    "doctor": "Dr. Emera McQuillan",
    "doctorEmail": "emcquillan2@about.me",
    "doctorId": 3,
    "patientEmail": "aperl2b@cloudflare.com",
    "items": [
      {
        "date": "2026-06-27",
        "time": "14:15",
        "type": "Dental Cleaning",
        "desc": "Teeth cleaning and cavity inspection",
        "doctorEmail": "emcquillan2@about.me",
        "doctorId": 3
      },
      {
        "date": "2026-08-01",
        "time": "12:45",
        "type": "Vaccination",
        "desc": "Routine immunization booster",
        "doctorEmail": "idumberrilld@toplist.cz",
        "doctorId": 14
      },
      {
        "date": "2026-12-24",
        "time": "08:45",
        "type": "Physiotherapy",
        "desc": "Mobility, pain and exercise plan",
        "doctorEmail": "idumberrilld@toplist.cz",
        "doctorId": 14
      }
    ]
  },
  {
    "nhs": "5974533852",
    "name": "Constantino Studders",
    "doctor": "Dr. Irvin Dumberrill",
    "doctorEmail": "idumberrilld@toplist.cz",
    "doctorId": 14,
    "patientEmail": "cstudders2c@google.ca",
    "items": [
      {
        "date": "2026-01-09",
        "time": "11:00",
        "type": "Diabetes Review",
        "desc": "HbA1c review, medication and diet",
        "doctorEmail": "idumberrilld@toplist.cz",
        "doctorId": 14
      },
      {
        "date": "2026-06-05",
        "time": "15:15",
        "type": "Hypertension Review",
        "desc": "BP trend review and medication",
        "doctorEmail": "zgalloway7@ca.gov",
        "doctorId": 8
      },
      {
        "date": "2026-08-22",
        "time": "14:45",
        "type": "Dermatology",
        "desc": "Skin inspection and treatment planning",
        "doctorEmail": "rblount8@pen.io",
        "doctorId": 9
      }
    ]
  },
  {
    "nhs": "5907940034",
    "name": "Lanny Quickfall",
    "doctor": "Dr. Merrily Harmson",
    "doctorEmail": "mharmsona@i2i.jp",
    "doctorId": 11,
    "patientEmail": "lquickfall2d@pen.io",
    "items": [
      {
        "date": "2026-02-22",
        "time": "15:15",
        "type": "Orthopedics",
        "desc": "Joint/muscle pain assessment",
        "doctorEmail": "mharmsona@i2i.jp",
        "doctorId": 11
      },
      {
        "date": "2026-04-15",
        "time": "14:45",
        "type": "Cardiology Consultation",
        "desc": "Discuss chest discomfort and risk factors",
        "doctorEmail": "rblount8@pen.io",
        "doctorId": 9
      },
      {
        "date": "2026-07-01",
        "time": "15:15",
        "type": "Cardiology Consultation",
        "desc": "Discuss chest discomfort and risk factors",
        "doctorEmail": "zgalloway7@ca.gov",
        "doctorId": 8
      }
    ]
  },
  {
    "nhs": "4148515472",
    "name": "Levon Flanigan",
    "doctor": "Dr. Rowland Blount",
    "doctorEmail": "rblount8@pen.io",
    "doctorId": 9,
    "patientEmail": "lflanigan2e@answers.com",
    "items": [
      {
        "date": "2026-01-08",
        "time": "13:00",
        "type": "Dermatology",
        "desc": "Skin inspection and treatment planning",
        "doctorEmail": "rblount8@pen.io",
        "doctorId": 9
      },
      {
        "date": "2026-06-19",
        "time": "08:00",
        "type": "Pediatrics",
        "desc": "Child growth, vaccination and development",
        "doctorEmail": "ehandlin4@gravatar.com",
        "doctorId": 5
      }
    ]
  },
  {
    "nhs": "2222769337",
    "name": "Chicky Woodroof",
    "doctor": "Dr. Erwin Handlin",
    "doctorEmail": "ehandlin4@gravatar.com",
    "doctorId": 5,
    "patientEmail": "cwoodroof2f@pagesperso-orange.fr",
    "items": [
      {
        "date": "2026-03-05",
        "time": "12:30",
        "type": "Dermatology",
        "desc": "Skin inspection and treatment planning",
        "doctorEmail": "ehandlin4@gravatar.com",
        "doctorId": 5
      },
      {
        "date": "2026-07-14",
        "time": "09:30",
        "type": "Dental Cleaning",
        "desc": "Teeth cleaning and cavity inspection",
        "doctorEmail": "ebeardsworth1@mac.com",
        "doctorId": 2
      }
    ]
  },
  {
    "nhs": "0163065462",
    "name": "Ula Baskerville",
    "doctor": "Dr. Monah Caghy",
    "doctorEmail": "mcaghy5@surveymonkey.com",
    "doctorId": 6,
    "patientEmail": "ubaskerville2g@shutterfly.com",
    "items": [
      {
        "date": "2025-11-17",
        "time": "16:45",
        "type": "General Check-up",
        "desc": "Routine health screening and vitals",
        "doctorEmail": "mcaghy5@surveymonkey.com",
        "doctorId": 6
      },
      {
        "date": "2026-01-24",
        "time": "09:15",
        "type": "Dental Cleaning",
        "desc": "Teeth cleaning and cavity inspection",
        "doctorEmail": "mharmsona@i2i.jp",
        "doctorId": 11
      },
      {
        "date": "2026-05-28",
        "time": "11:00",
        "type": "General Check-up",
        "desc": "Routine health screening and vitals",
        "doctorEmail": "zgalloway7@ca.gov",
        "doctorId": 8
      }
    ]
  },
  {
    "nhs": "8070302771",
    "name": "Welch Treadger",
    "doctor": "Dr. Rowland Blount",
    "doctorEmail": "rblount8@pen.io",
    "doctorId": 9,
    "patientEmail": "wtreadger2h@163.com",
    "items": [
      {
        "date": "2026-04-01",
        "time": "09:45",
        "type": "Hypertension Review",
        "desc": "BP trend review and medication",
        "doctorEmail": "rblount8@pen.io",
        "doctorId": 9
      },
      {
        "date": "2026-06-24",
        "time": "16:00",
        "type": "ENT Examination",
        "desc": "Ear, nose and throat review",
        "doctorEmail": "sgivese@wsj.com",
        "doctorId": 15
      },
      {
        "date": "2026-07-25",
        "time": "12:30",
        "type": "ENT Examination",
        "desc": "Ear, nose and throat review",
        "doctorEmail": "mharmsona@i2i.jp",
        "doctorId": 11
      }
    ]
  },
  {
    "nhs": "4590278510",
    "name": "Kerstin Cuphus",
    "doctor": "Dr. Si Pawling",
    "doctorEmail": "spawling9@princeton.edu",
    "doctorId": 10,
    "patientEmail": "kcuphus2i@liveinternet.ru",
    "items": [
      {
        "date": "2026-04-07",
        "time": "14:00",
        "type": "Hypertension Review",
        "desc": "BP trend review and medication",
        "doctorEmail": "spawling9@princeton.edu",
        "doctorId": 10
      },
      {
        "date": "2026-05-29",
        "time": "15:30",
        "type": "Physiotherapy",
        "desc": "Mobility, pain and exercise plan",
        "doctorEmail": "zgalloway7@ca.gov",
        "doctorId": 8
      },
      {
        "date": "2026-08-24",
        "time": "16:45",
        "type": "Hypertension Review",
        "desc": "BP trend review and medication",
        "doctorEmail": "rphilipard6@mayoclinic.com",
        "doctorId": 7
      }
    ]
  },
  {
    "nhs": "9475373012",
    "name": "Puff Lumsdale",
    "doctor": "Dr. Rowland Blount",
    "doctorEmail": "rblount8@pen.io",
    "doctorId": 9,
    "patientEmail": "plumsdale2j@time.com",
    "items": [
      {
        "date": "2026-09-13",
        "time": "12:30",
        "type": "Physiotherapy",
        "desc": "Mobility, pain and exercise plan",
        "doctorEmail": "rblount8@pen.io",
        "doctorId": 9
      },
      {
        "date": "2026-09-20",
        "time": "10:00",
        "type": "Hypertension Review",
        "desc": "BP trend review and medication",
        "doctorEmail": "nkyrkeman3@foxnews.com",
        "doctorId": 4
      },
      {
        "date": "2026-12-09",
        "time": "14:00",
        "type": "Follow-up",
        "desc": "Review of recent results and symptoms",
        "doctorEmail": "idumberrilld@toplist.cz",
        "doctorId": 14
      }
    ]
  },
  {
    "nhs": "2733019406",
    "name": "Lotti Bartholomew",
    "doctor": "Dr. Hi Willingam",
    "doctorEmail": "hwillingamc@springer.com",
    "doctorId": 13,
    "patientEmail": "lbartholomew2k@last.fm",
    "items": [
      {
        "date": "2026-07-14",
        "time": "15:30",
        "type": "ENT Examination",
        "desc": "Ear, nose and throat review",
        "doctorEmail": "hwillingamc@springer.com",
        "doctorId": 13
      },
      {
        "date": "2026-12-11",
        "time": "13:45",
        "type": "General Check-up",
        "desc": "Routine health screening and vitals",
        "doctorEmail": "mharmsona@i2i.jp",
        "doctorId": 11
      }
    ]
  },
  {
    "nhs": "1678031216",
    "name": "Malina Domerq",
    "doctor": "Dr. Cordell Toor",
    "doctorEmail": "ctoorb@psu.edu",
    "doctorId": 12,
    "patientEmail": "mdomerq2l@plala.or.jp",
    "items": [
      {
        "date": "2026-01-15",
        "time": "15:00",
        "type": "Follow-up",
        "desc": "Review of recent results and symptoms",
        "doctorEmail": "ctoorb@psu.edu",
        "doctorId": 12
      },
      {
        "date": "2026-11-29",
        "time": "14:45",
        "type": "Follow-up",
        "desc": "Review of recent results and symptoms",
        "doctorEmail": "zgalloway7@ca.gov",
        "doctorId": 8
      }
    ]
  },
  {
    "nhs": "5752908701",
    "name": "Agace Brettoner",
    "doctor": "Dr. Irvin Dumberrill",
    "doctorEmail": "idumberrilld@toplist.cz",
    "doctorId": 14,
    "patientEmail": "abrettoner2m@reverbnation.com",
    "items": [
      {
        "date": "2026-03-05",
        "time": "16:30",
        "type": "ENT Examination",
        "desc": "Ear, nose and throat review",
        "doctorEmail": "idumberrilld@toplist.cz",
        "doctorId": 14
      },
      {
        "date": "2026-05-10",
        "time": "13:30",
        "type": "Physiotherapy",
        "desc": "Mobility, pain and exercise plan",
        "doctorEmail": "mcaghy5@surveymonkey.com",
        "doctorId": 6
      },
      {
        "date": "2026-06-01",
        "time": "10:30",
        "type": "General Check-up",
        "desc": "Routine health screening and vitals",
        "doctorEmail": "vrilton0@discuz.net",
        "doctorId": 1
      }
    ]
  },
  {
    "nhs": "0742718808",
    "name": "Carlie Clamp",
    "doctor": "Dr. Hi Willingam",
    "doctorEmail": "hwillingamc@springer.com",
    "doctorId": 13,
    "patientEmail": "cclamp2n@zdnet.com",
    "items": [
      {
        "date": "2026-01-31",
        "time": "10:30",
        "type": "Cardiology Consultation",
        "desc": "Discuss chest discomfort and risk factors",
        "doctorEmail": "hwillingamc@springer.com",
        "doctorId": 13
      },
      {
        "date": "2026-03-22",
        "time": "11:30",
        "type": "Cardiology Consultation",
        "desc": "Discuss chest discomfort and risk factors",
        "doctorEmail": "mcaghy5@surveymonkey.com",
        "doctorId": 6
      },
      {
        "date": "2026-05-10",
        "time": "09:15",
        "type": "Orthopedics",
        "desc": "Joint/muscle pain assessment",
        "doctorEmail": "idumberrilld@toplist.cz",
        "doctorId": 14
      }
    ]
  },
  {
    "nhs": "6416503409",
    "name": "Cordey Stratz",
    "doctor": "Dr. Cordell Toor",
    "doctorEmail": "ctoorb@psu.edu",
    "doctorId": 12,
    "patientEmail": "cstratz2o@cbc.ca",
    "items": [
      {
        "date": "2025-11-10",
        "time": "16:45",
        "type": "ENT Examination",
        "desc": "Ear, nose and throat review",
        "doctorEmail": "ctoorb@psu.edu",
        "doctorId": 12
      },
      {
        "date": "2025-12-05",
        "time": "14:15",
        "type": "Cardiology Consultation",
        "desc": "Discuss chest discomfort and risk factors",
        "doctorEmail": "spawling9@princeton.edu",
        "doctorId": 10
      }
    ]
  },
  {
    "nhs": "1585276065",
    "name": "Lorain Langcastle",
    "doctor": "Dr. Rad Philipard",
    "doctorEmail": "rphilipard6@mayoclinic.com",
    "doctorId": 7,
    "patientEmail": "llangcastle2p@statcounter.com",
    "items": [
      {
        "date": "2026-03-31",
        "time": "16:15",
        "type": "General Check-up",
        "desc": "Routine health screening and vitals",
        "doctorEmail": "rphilipard6@mayoclinic.com",
        "doctorId": 7
      },
      {
        "date": "2026-08-30",
        "time": "16:15",
        "type": "General Check-up",
        "desc": "Routine health screening and vitals",
        "doctorEmail": "ehandlin4@gravatar.com",
        "doctorId": 5
      }
    ]
  },
  {
    "nhs": "7096153047",
    "name": "Cinnamon Pideon",
    "doctor": "Dr. Violante Rilton",
    "doctorEmail": "vrilton0@discuz.net",
    "doctorId": 1,
    "patientEmail": "cpideon2q@engadget.com",
    "items": [
      {
        "date": "2026-03-11",
        "time": "16:00",
        "type": "Follow-up",
        "desc": "Review of recent results and symptoms",
        "doctorEmail": "vrilton0@discuz.net",
        "doctorId": 1
      },
      {
        "date": "2026-04-06",
        "time": "09:45",
        "type": "Follow-up",
        "desc": "Review of recent results and symptoms",
        "doctorEmail": "spawling9@princeton.edu",
        "doctorId": 10
      },
      {
        "date": "2026-12-12",
        "time": "08:15",
        "type": "Diabetes Review",
        "desc": "HbA1c review, medication and diet",
        "doctorEmail": "vrilton0@discuz.net",
        "doctorId": 1
      }
    ]
  },
  {
    "nhs": "0916757552",
    "name": "Web Oxnam",
    "doctor": "Dr. Monah Caghy",
    "doctorEmail": "mcaghy5@surveymonkey.com",
    "doctorId": 6,
    "patientEmail": "woxnam2r@pbs.org",
    "items": [
      {
        "date": "2026-01-12",
        "time": "13:15",
        "type": "Dermatology",
        "desc": "Skin inspection and treatment planning",
        "doctorEmail": "mcaghy5@surveymonkey.com",
        "doctorId": 6
      },
      {
        "date": "2026-03-19",
        "time": "09:30",
        "type": "Vaccination",
        "desc": "Routine immunization booster",
        "doctorEmail": "rphilipard6@mayoclinic.com",
        "doctorId": 7
      },
      {
        "date": "2026-08-01",
        "time": "08:15",
        "type": "Diabetes Review",
        "desc": "HbA1c review, medication and diet",
        "doctorEmail": "nkyrkeman3@foxnews.com",
        "doctorId": 4
      }
    ]
  }
]
